<nu xmlns:xsl="http://www.w3.org/1999/XSL/Transform" attrib="this-is-att-value"><gamma><rho xml:lang="nb" xml:id="id1"><alpha xml:id="id2"/><epsilon><upsilon object="content" xml:lang="nb"><pi xml:lang="en-GB" xml:id="id3"/><omega><any delete="_blank" xml:lang="nb"/><lambda xml:id="id4"/><delta xml:lang="en-GB"/><psi><zeta or="attribute-value"><rho string="attribute-value" xml:lang="no"/><epsilon xml:lang="no-nb"><upsilon abort="attribute-value" xml:lang="en-GB"><upsilon xml:id="id5"/><eta xml:id="id6"><beta xml:lang="en-GB" xml:id="id7"><lambda content="true" xml:lang="en" xml:id="id8"/><any token="_blank" xml:id="id9"/><rho content="attribute-value" xml:lang="no-nb" xml:id="id10"><tau><green>This text must be green</green></tau></rho></beta></eta></upsilon></epsilon></zeta></psi></omega></upsilon></epsilon></rho></gamma></nu>