<beta xmlns:xsl="http://www.w3.org/1999/XSL/Transform" object="_blank"><iota><theta number="123456789" xml:lang="nb" xml:id="id1"><delta true="solid 1px green"><chi xml:lang="nb" xml:id="id2"><psi number="content"><beta name="attribute value" xml:id="id3"><omega object="attribute"><beta><nu attribute="this-is-att-value" xml:lang="no"/><rho content="attribute" xml:lang="en-US"><delta/><epsilon false="true" xml:lang="en-US"><mu src="false" xml:id="id4"/><alpha object="attribute value" xml:lang="en-GB" xml:id="id5"/><sigma desciption="_blank"/><rho xml:id="id6"><green>This text must be green</green></rho></epsilon></rho></beta></omega></beta></psi></chi></delta></theta></iota></beta>