<eta xmlns:xsl="http://www.w3.org/1999/XSL/Transform" xml:id="id1"><gamma xml:lang="en" xml:id="id2"><chi/><lambda xml:id="id3"/><xi delete="this-is-att-value"><psi desciption="attribute" xml:lang="en-US" xml:id="id4"><tau xml:id="id5"/><omega content="true" xml:lang="no-nb" xml:id="id6"/><phi xml:lang="en-US" xml:id="id7"><mu number="false"/><nu xml:lang="en-US" xml:id="id8"><pi><pi title="content" xml:lang="no" xml:id="id9"><alpha><gamma name="content"/><theta string="solid 1px green" xml:lang="en" xml:id="id10"><omega><alpha src="solid 1px green" xml:lang="nb"><delta xml:lang="en-US"/><upsilon delete="_blank" xml:lang="nb" xml:id="id11"/><omicron xml:lang="en-GB" xml:id="id12"><upsilon delete="this-is-att-value" xml:lang="en-GB"><kappa xml:id="id13"/><omega class="true" xml:lang="no" xml:id="id14"><green>This text must be green</green></omega></upsilon></omicron></alpha></omega></theta></alpha></pi></pi></nu></phi></psi></xi></gamma></eta>