<omicron xmlns:xsl="http://www.w3.org/1999/XSL/Transform" src="123456789" xml:id="id1"><xi xml:id="id2"/><phi attribute="this.nodeValue" xml:lang="no-nb"/><beta att="false" xml:lang="no"/><any attr="content" xml:lang="en" xml:id="id3"><omicron title="false" xml:lang="en-US"><eta number="attribute-value" xml:lang="no"><phi token="100%"><alpha xml:lang="nb" xml:id="id4"><pi number="attribute" xml:id="id5"><theta string="true"><delta true="false" xml:id="id6"><phi object="123456789" xml:lang="en-GB"/><epsilon src="this-is-att-value" xml:lang="nb" xml:id="id7"><green>This text must be green</green></epsilon></delta></theta></pi></alpha></phi></eta></omicron></any></omicron>