<xi xmlns:xsl="http://www.w3.org/1999/XSL/Transform"><eta content="_blank" xml:lang="no-nb" xml:id="id1"/><omega number="attribute value"/><omicron xml:lang="en-GB"><epsilon delete="attribute-value" xml:lang="en-GB"><lambda att="100%" xml:id="id2"/><iota/><kappa xml:lang="no-nb"/><epsilon false="this-is-att-value" xml:lang="en"/><omega/><chi desciption="content" xml:lang="en"/><tau xml:lang="en-US" xml:id="id3"><rho/><lambda/><theta attribute="_blank"><epsilon xml:lang="nb" xml:id="id4"><any object="content" xml:lang="no" xml:id="id5"/><any attribute="123456789"><chi content="true" xml:lang="en"/><upsilon><gamma class="attribute value"><rho src="100%" xml:id="id6"><beta xml:id="id7"><green>This text must be green</green></beta></rho></gamma></upsilon></any></epsilon></theta></tau></epsilon></omicron></xi>