<mu xmlns:xsl="http://www.w3.org/1999/XSL/Transform" attr="123456789"><lambda xml:lang="nb" xml:id="id1"/><delta desciption="attribute-value"><xi or="_blank" xml:lang="en"><omega xml:id="id2"/><delta insert="this-is-att-value"/><any><theta number="content"/><xi xml:lang="nb"/><psi xml:lang="nb"/><rho token="123456789" xml:lang="nb"/><phi xml:id="id3"/><pi><xi class="_blank" xml:id="id4"/><pi xml:id="id5"><xi><beta><chi xml:lang="no-nb" xml:id="id6"/><gamma xml:id="id7"/><chi content="false" xml:lang="en-GB" xml:id="id8"/><gamma class="attribute" xml:id="id9"><green>This text must be green</green></gamma></beta></xi></pi></pi></any></xi></delta></mu>