<upsilon xmlns:xsl="http://www.w3.org/1999/XSL/Transform" name="123456789"><theta xml:lang="no"><nu attrib="attribute" xml:id="id1"/><chi object="false"><pi xml:lang="no"><rho false="attribute-value" xml:id="id2"/><lambda><alpha string="false" xml:lang="en-GB"><iota xml:lang="en-GB"><rho true="_blank" xml:id="id3"><iota src="123456789" xml:lang="no-nb"><upsilon xml:lang="en-US" xml:id="id4"><zeta or="attribute value"><gamma or="solid 1px green" xml:id="id5"><rho attr="another attribute value"><phi xml:id="id6"/><chi title="123456789"><xi/><pi number="solid 1px green" xml:id="id7"><theta xml:lang="en-GB"/><theta xml:lang="no" xml:id="id8"><iota attribute="attribute value" xml:lang="en-US" xml:id="id9"><green>This text must be green</green></iota></theta></pi></chi></rho></gamma></zeta></upsilon></iota></rho></iota></alpha></lambda></pi></chi></theta></upsilon>